uncertainty_rejection/__init__.py
uncertainty_rejection/analysis.py
uncertainty_rejection/datasets.py
uncertainty_rejection/plotting.py
uncertainty_rejection/utils.py
uncertainty_rejection-0.2.0.dist-info/LICENSE
uncertainty_rejection-0.2.0.dist-info/WHEEL
uncertainty_rejection-0.2.0.dist-info/METADATA
uncertainty_rejection-0.2.0.dist-info/RECORD
