Metadata-Version: 2.1
Name: uncertainty-rejection
Version: 0.2.0
Summary: Analysis of uncertainty estimates for classification with rejection.
Home-page: https://github.com/arthur-thuy/uncertainty-rejection
License: Apache-2.0
Author: Arthur Thuy
Author-email: arthur.thuy@ugent.be
Maintainer: Arthur Thuy
Maintainer-email: arthur.thuy@ugent.be
Requires-Python: >=3.8
Classifier: Development Status :: 3 - Alpha
Classifier: License :: OSI Approved :: Apache Software License
Classifier: Operating System :: OS Independent
Classifier: Programming Language :: Python :: 3
Classifier: Programming Language :: Python :: 3.8
Classifier: Programming Language :: Python :: 3.9
Classifier: Programming Language :: Python :: 3.10
Classifier: Programming Language :: Python :: 3.11
Classifier: Topic :: Scientific/Engineering :: Artificial Intelligence
Requires-Dist: matplotlib (>=3.6.2)
Requires-Dist: numpy (>=1.23.5)
Requires-Dist: scipy (>=1.9.3)
Requires-Dist: tabulate (>=0.9.0)
Project-URL: Documentation, https://uncertainty-rejection.readthedocs.io/en/latest/
Project-URL: Repository, https://github.com/arthur-thuy/uncertainty-rejection
